Metadata-Version: 1.0
Name: glenn-distributions
Version: 0.2
Summary: Gaussian & Binomial distributions
Home-page: UNKNOWN
Author: Glenn Teh
Author-email: UNKNOWN
License: UNKNOWN
Platform: UNKNOWN
